zope.meta-1.0-py3.11-nspkg.pth
zope/meta/__init__.py
zope/meta/config_package.py
zope/meta/multi_call.py
zope/meta/re_enable_actions.py
zope/meta/set_branch_protection_rules.py
zope/meta/update_python_support.py
zope/meta/buildout-recipe/coveragerc.j2
zope/meta/buildout-recipe/packages.txt
zope/meta/buildout-recipe/tox.ini.j2
zope/meta/c-code/coveragerc.j2
zope/meta/c-code/manylinux-install.sh.j2
zope/meta/c-code/manylinux.sh
zope/meta/c-code/packages.txt
zope/meta/c-code/tests-cache.j2
zope/meta/c-code/tests-download.j2
zope/meta/c-code/tests-strategy.j2
zope/meta/c-code/tests.yml.j2
zope/meta/c-code/tox.ini.j2
zope/meta/default/CONTRIBUTING.md
zope/meta/default/MANIFEST.in.j2
zope/meta/default/editorconfig.txt
zope/meta/default/gitignore.j2
zope/meta/default/pre-commit-config.yaml.j2
zope/meta/default/pre-commit.yml.j2
zope/meta/default/readthedocs.yaml.j2
zope/meta/default/setup.cfg.j2
zope/meta/default/tests.yml.j2
zope/meta/default/tox-docs.j2
zope/meta/default/tox-envlist.j2
zope/meta/default/tox-lint.j2
zope/meta/default/tox-release-check.j2
zope/meta/default/tox-testenv.j2
zope/meta/pure-python/packages.txt
zope/meta/pure-python/tox.ini.j2
zope/meta/shared/__init__.py
zope/meta/shared/call.py
zope/meta/shared/git.py
zope/meta/shared/packages.py
zope/meta/shared/path.py
zope/meta/tests/__init__.py
zope/meta/tests/test_config_package.py
zope/meta/toolkit/packages.txt
zope/meta/toolkit/tox.ini.j2
zope/meta/zope-product/packages.txt
zope/meta/zope-product/tox.ini.j2
zope.meta-1.0.dist-info/LICENSE.txt
zope.meta-1.0.dist-info/METADATA
zope.meta-1.0.dist-info/WHEEL
zope.meta-1.0.dist-info/entry_points.txt
zope.meta-1.0.dist-info/namespace_packages.txt
zope.meta-1.0.dist-info/top_level.txt
zope.meta-1.0.dist-info/RECORD
