Metadata-Version: 2.1
Name: zope.meta
Version: 1.0
Summary: Helper functions for package management
Home-page: https://github.com/zopefoundation/meta
Author: Zope Foundation and Contributors
Author-email: zope-dev@zope.dev
License: ZPL 2.1
Project-URL: Documentation, https://zopemeta.readthedocs.io
Project-URL: Issue Tracker, https://github.com/zopefoundation/meta/issues
Project-URL: Sources, https://github.com/zopefoundation/meta
Keywords: zope packaging
Classifier: Development Status :: 3 - Alpha
Classifier: Intended Audience :: Developers
Classifier: License :: OSI Approved :: Zope Public License
Classifier: Programming Language :: Python
Classifier: Programming Language :: Python :: 3
Classifier: Programming Language :: Python :: 3.8
Classifier: Programming Language :: Python :: 3.9
Classifier: Programming Language :: Python :: 3.10
Classifier: Programming Language :: Python :: 3.11
Classifier: Programming Language :: Python :: 3.12
Classifier: Programming Language :: Python :: 3.13
Classifier: Programming Language :: Python :: Implementation :: CPython
Classifier: Natural Language :: English
Classifier: Operating System :: OS Independent
Requires-Python: >=3.8
License-File: LICENSE.txt
Requires-Dist: setuptools
Requires-Dist: check-python-versions
Requires-Dist: Jinja2
Requires-Dist: packaging
Requires-Dist: pyupgrade
Requires-Dist: requests
Requires-Dist: tomlkit
Requires-Dist: tox
Requires-Dist: zest.releaser
Provides-Extra: docs
Requires-Dist: Sphinx; extra == "docs"
Requires-Dist: furo; extra == "docs"
Provides-Extra: test
Requires-Dist: zope.testrunner; extra == "test"
